{
    "part_5": {
        "101": "B",
        "102": "D",
        "103": "D",
        "104": "B",
        "105": "B",
        "106": "A",
        "107": "C",
        "108": "B",
        "109": "D",
        "110": "D",
        "111": "A",
        "112": "B",
        "113": "C",
        "114": "C",
        "115": "C",
        "116": "B",
        "117": "D",
        "118": "A",
        "119": "A",
        "120": "A",
        "121": "B",
        "122": "D",
        "123": "C",
        "124": "C",
        "125": "A",
        "126": "D",
        "127": "D",
        "128": "A",
        "129": "C",
        "130": "B"
    },
    "part_6": {
        "131": "D",
        "132": "B",
        "133": "D",
        "134": "D",
        "135": "B",
        "136": "C",
        "137": "C",
        "138": "C",
        "139": "C",
        "140": "A",
        "141": "B",
        "142": "D",
        "143": "C",
        "144": "A",
        "145": "A",
        "146": "D"
    },
    "part_7": {
        "147": "D",
        "148": "C",
        "149": "B",
        "150": "D",
        "151": "B",
        "152": "B",
        "153": "A",
        "154": "A",
        "155": "B",
        "156": "A",
        "157": "C",
        "158": "B",
        "159": "A",
        "160": "A",
        "161": "D",
        "162": "C",
        "163": "C",
        "164": "D",
        "165": "D",
        "166": "C",
        "167": "A",
        "168": "A",
        "169": "B",
        "170": "B",
        "171": "C",
        "172": "B",
        "173": "D",
        "174": "A",
        "175": "C",
        "176": "C",
        "177": "A",
        "178": "D",
        "179": "B",
        "180": "B",
        "181": "A",
        "182": "B",
        "183": "B",
        "184": "D",
        "185": "D",
        "186": "D",
        "187": "C",
        "188": "B",
        "189": "C",
        "190": "A",
        "191": "A",
        "192": "C",
        "193": "B",
        "194": "D",
        "195": "D",
        "196": "B",
        "197": "D",
        "198": "C",
        "199": "A",
        "200": "D"
    }
}
